Workbook

Sheet 选品评分
A1: 选品评分模板 · 淘系男性成人用品（蓝色=输入，黑色=公式自动算；权重/锚点见「参数」表）
A3: 商品名称 | B3: 合规硬门 (命中红线?是/否) | C3: 售价 | D3: 货源成本 | E3: 平台扣点率 | F3: 物流 | G3: 包装 | H3: 毛利率 | I3: 毛利率得分 | J3: 绝对利润额 | K3: 绝对利润额得分 | L3: 利润分 | M3: 月搜索人气 | N3: 在线商品数 | O3: 趋势 (上升/平稳/下降) | P3: 需求分 | Q3: 竞争度 | R3: 竞争分 | S3: 趋势分 | T3: 蓝海度分 | U3: 复购分 (0-10) | V3: 合规难度分 (0-10) | W3: 加权原始分 | X3: 总分 | Y3: 决策
A4: 润滑液(高频快消) | B4: 否 | C4: 39 | D4: 8 | E4: 0.05 | F4: 3 | G4: 1.5 | H4: =IF($A4="",0,IF(C4=0,0,(C4-D4-C4*E4-F4-G4)/C4)) -> 0.62948718 | I4: =IF($A4="",0,IF(H4>=参数!$D$2,参数!$E$2,IF(H4>=参数!$D$3,参数!$E$3,IF(H4>=参数!$D$4,参数!$E$4,IF(H4>=参数!$D$5,参数!$E$5,参数!$E$6))))) -> 10 | J4: =IF($A4="",0,C4*H4) -> 24.55 | K4: =IF($A4="",0,IF(J4>=参数!$G$2,参数!$H$2,IF(J4>=参数!$G$3,参数!$H$3,IF(J4>=参数!$G$4,参数!$H$4,IF(J4>=参数!$G$5,参数!$H$5,参数!$H$6))))) -> 6 | L4: =IF($A4="",0,I4*0.6+K4*0.4) -> 8.4 | M4: 8000 | N4: 12000 | O4: 上升 | P4: =IF($A4="",0,IF(M4>=参数!$J$2,参数!$K$2,IF(M4>=参数!$J$3,参数!$K$3,IF(M4>=参数!$J$4,参数!$K$4,IF(M4>=参数!$J$5,参数!$K$5,参数!$K$6))))) -> 8 | Q4: =IF($A4="",0,IF(M4=0,0,N4/M4)) -> 1.5 | R4: =IF($A4="",0,IF(Q4<参数!$M$2,参数!$N$2,IF(Q4<参数!$M$3,参数!$N$3,IF(Q4<参数!$M$4,参数!$N$4,IF(Q4<参数!$M$5,参数!$N$5,2))))) -> 8 | S4: =IF($A4="",0,IF(O4="上升",10,IF(O4="平稳",6,IF(O4="下降",2,6)))) -> 10 | T4: =IF($A4="",0,P4*0.4+R4*0.4+S4*0.2) -> 8.4 | U4: 10 | V4: 7 | W4: =IF($A4="",0,(L4*参数!$B$2+T4*参数!$B$3+U4*参数!$B$4+V4*参数!$B$5)*10) -> 85.9 | X4: =IF($A4="","",IF(B4="是",0,IF(OR(L4<参数!$B$8,T4<参数!$B$9),MIN(W4,参数!$B$10),W4))) -> 85.9 | Y4: =IF($A4="","",IF(X4>=80,"主推",IF(X4>=65,"测款",IF(X4>=50,"观察","放弃")))) -> 主推
A5: 延时喷剂(高敏感) | B5: 否 | C5: 89 | D5: 20 | E5: 0.05 | F5: 4 | G5: 2 | H5: =IF($A5="",0,IF(C5=0,0,(C5-D5-C5*E5-F5-G5)/C5)) -> 0.65786517 | I5: =IF($A5="",0,IF(H5>=参数!$D$2,参数!$E$2,IF(H5>=参数!$D$3,参数!$E$3,IF(H5>=参数!$D$4,参数!$E$4,IF(H5>=参数!$D$5,参数!$E$5,参数!$E$6))))) -> 10 | J5: =IF($A5="",0,C5*H5) -> 58.55 | K5: =IF($A5="",0,IF(J5>=参数!$G$2,参数!$H$2,IF(J5>=参数!$G$3,参数!$H$3,IF(J5>=参数!$G$4,参数!$H$4,IF(J5>=参数!$G$5,参数!$H$5,参数!$H$6))))) -> 10 | L5: =IF($A5="",0,I5*0.6+K5*0.4) -> 10 | M5: 6000 | N5: 30000 | O5: 平稳 | P5: =IF($A5="",0,IF(M5>=参数!$J$2,参数!$K$2,IF(M5>=参数!$J$3,参数!$K$3,IF(M5>=参数!$J$4,参数!$K$4,IF(M5>=参数!$J$5,参数!$K$5,参数!$K$6))))) -> 8 | Q5: =IF($A5="",0,IF(M5=0,0,N5/M5)) -> 5 | R5: =IF($A5="",0,IF(Q5<参数!$M$2,参数!$N$2,IF(Q5<参数!$M$3,参数!$N$3,IF(Q5<参数!$M$4,参数!$N$4,IF(Q5<参数!$M$5,参数!$N$5,2))))) -> 6 | S5: =IF($A5="",0,IF(O5="上升",10,IF(O5="平稳",6,IF(O5="下降",2,6)))) -> 6 | T5: =IF($A5="",0,P5*0.4+R5*0.4+S5*0.2) -> 6.8 | U5: 7 | V5: 3 | W5: =IF($A5="",0,(L5*参数!$B$2+T5*参数!$B$3+U5*参数!$B$4+V5*参数!$B$5)*10) -> 72.4 | X5: =IF($A5="","",IF(B5="是",0,IF(OR(L5<参数!$B$8,T5<参数!$B$9),MIN(W5,参数!$B$10),W5))) -> 72.4 | Y5: =IF($A5="","",IF(X5>=80,"主推",IF(X5>=65,"测款",IF(X5>=50,"观察","放弃")))) -> 测款
A6: 违法添加壮阳口服 | B6: 是 | C6: 59 | D6: 10 | E6: 0.05 | F6: 3 | G6: 1 | H6: =IF($A6="",0,IF(C6=0,0,(C6-D6-C6*E6-F6-G6)/C6)) -> 0.71271186 | I6: =IF($A6="",0,IF(H6>=参数!$D$2,参数!$E$2,IF(H6>=参数!$D$3,参数!$E$3,IF(H6>=参数!$D$4,参数!$E$4,IF(H6>=参数!$D$5,参数!$E$5,参数!$E$6))))) -> 10 | J6: =IF($A6="",0,C6*H6) -> 42.05 | K6: =IF($A6="",0,IF(J6>=参数!$G$2,参数!$H$2,IF(J6>=参数!$G$3,参数!$H$3,IF(J6>=参数!$G$4,参数!$H$4,IF(J6>=参数!$G$5,参数!$H$5,参数!$H$6))))) -> 8 | L6: =IF($A6="",0,I6*0.6+K6*0.4) -> 9.2 | M6: 5000 | N6: 8000 | O6: 上升 | P6: =IF($A6="",0,IF(M6>=参数!$J$2,参数!$K$2,IF(M6>=参数!$J$3,参数!$K$3,IF(M6>=参数!$J$4,参数!$K$4,IF(M6>=参数!$J$5,参数!$K$5,参数!$K$6))))) -> 8 | Q6: =IF($A6="",0,IF(M6=0,0,N6/M6)) -> 1.6 | R6: =IF($A6="",0,IF(Q6<参数!$M$2,参数!$N$2,IF(Q6<参数!$M$3,参数!$N$3,IF(Q6<参数!$M$4,参数!$N$4,IF(Q6<参数!$M$5,参数!$N$5,2))))) -> 8 | S6: =IF($A6="",0,IF(O6="上升",10,IF(O6="平稳",6,IF(O6="下降",2,6)))) -> 10 | T6: =IF($A6="",0,P6*0.4+R6*0.4+S6*0.2) -> 8.4 | U6: 6 | V6: 0 | W6: =IF($A6="",0,(L6*参数!$B$2+T6*参数!$B$3+U6*参数!$B$4+V6*参数!$B$5)*10) -> 67.8 | X6: =IF($A6="","",IF(B6="是",0,IF(OR(L6<参数!$B$8,T6<参数!$B$9),MIN(W6,参数!$B$10),W6))) -> 0 | Y6: =IF($A6="","",IF(X6>=80,"主推",IF(X6>=65,"测款",IF(X6>=50,"观察","放弃")))) -> 放弃
A7: 低价避孕套(薄利) | B7: 否 | C7: 9.9 | D7: 5 | E7: 0.05 | F7: 2.5 | G7: 1 | H7: =IF($A7="",0,IF(C7=0,0,(C7-D7-C7*E7-F7-G7)/C7)) -> 0.091414141 | I7: =IF($A7="",0,IF(H7>=参数!$D$2,参数!$E$2,IF(H7>=参数!$D$3,参数!$E$3,IF(H7>=参数!$D$4,参数!$E$4,IF(H7>=参数!$D$5,参数!$E$5,参数!$E$6))))) -> 2 | J7: =IF($A7="",0,C7*H7) -> 0.905 | K7: =IF($A7="",0,IF(J7>=参数!$G$2,参数!$H$2,IF(J7>=参数!$G$3,参数!$H$3,IF(J7>=参数!$G$4,参数!$H$4,IF(J7>=参数!$G$5,参数!$H$5,参数!$H$6))))) -> 2 | L7: =IF($A7="",0,I7*0.6+K7*0.4) -> 2 | M7: 20000 | N7: 40000 | O7: 上升 | P7: =IF($A7="",0,IF(M7>=参数!$J$2,参数!$K$2,IF(M7>=参数!$J$3,参数!$K$3,IF(M7>=参数!$J$4,参数!$K$4,IF(M7>=参数!$J$5,参数!$K$5,参数!$K$6))))) -> 10 | Q7: =IF($A7="",0,IF(M7=0,0,N7/M7)) -> 2 | R7: =IF($A7="",0,IF(Q7<参数!$M$2,参数!$N$2,IF(Q7<参数!$M$3,参数!$N$3,IF(Q7<参数!$M$4,参数!$N$4,IF(Q7<参数!$M$5,参数!$N$5,2))))) -> 8 | S7: =IF($A7="",0,IF(O7="上升",10,IF(O7="平稳",6,IF(O7="下降",2,6)))) -> 10 | T7: =IF($A7="",0,P7*0.4+R7*0.4+S7*0.2) -> 9.2 | U7: 10 | V7: 5 | W7: =IF($A7="",0,(L7*参数!$B$2+T7*参数!$B$3+U7*参数!$B$4+V7*参数!$B$5)*10) -> 66.1 | X7: =IF($A7="","",IF(B7="是",0,IF(OR(L7<参数!$B$8,T7<参数!$B$9),MIN(W7,参数!$B$10),W7))) -> 50 | Y7: =IF($A7="","",IF(X7>=80,"主推",IF(X7>=65,"测款",IF(X7>=50,"观察","放弃")))) -> 观察
H8: =IF($A8="",0,IF(C8=0,0,(C8-D8-C8*E8-F8-G8)/C8)) -> 0 | I8: =IF($A8="",0,IF(H8>=参数!$D$2,参数!$E$2,IF(H8>=参数!$D$3,参数!$E$3,IF(H8>=参数!$D$4,参数!$E$4,IF(H8>=参数!$D$5,参数!$E$5,参数!$E$6))))) -> 0 | J8: =IF($A8="",0,C8*H8) -> 0 | K8: =IF($A8="",0,IF(J8>=参数!$G$2,参数!$H$2,IF(J8>=参数!$G$3,参数!$H$3,IF(J8>=参数!$G$4,参数!$H$4,IF(J8>=参数!$G$5,参数!$H$5,参数!$H$6))))) -> 0 | L8: =IF($A8="",0,I8*0.6+K8*0.4) -> 0 | P8: =IF($A8="",0,IF(M8>=参数!$J$2,参数!$K$2,IF(M8>=参数!$J$3,参数!$K$3,IF(M8>=参数!$J$4,参数!$K$4,IF(M8>=参数!$J$5,参数!$K$5,参数!$K$6))))) -> 0 | Q8: =IF($A8="",0,IF(M8=0,0,N8/M8)) -> 0 | R8: =IF($A8="",0,IF(Q8<参数!$M$2,参数!$N$2,IF(Q8<参数!$M$3,参数!$N$3,IF(Q8<参数!$M$4,参数!$N$4,IF(Q8<参数!$M$5,参数!$N$5,2))))) -> 0 | S8: =IF($A8="",0,IF(O8="上升",10,IF(O8="平稳",6,IF(O8="下降",2,6)))) -> 0 | T8: =IF($A8="",0,P8*0.4+R8*0.4+S8*0.2) -> 0 | W8: =IF($A8="",0,(L8*参数!$B$2+T8*参数!$B$3+U8*参数!$B$4+V8*参数!$B$5)*10) -> 0 | X8: =IF($A8="","",IF(B8="是",0,IF(OR(L8<参数!$B$8,T8<参数!$B$9),MIN(W8,参数!$B$10),W8))) | Y8: =IF($A8="","",IF(X8>=80,"主推",IF(X8>=65,"测款",IF(X8>=50,"观察","放弃"))))
H9: =IF($A9="",0,IF(C9=0,0,(C9-D9-C9*E9-F9-G9)/C9)) -> 0 | I9: =IF($A9="",0,IF(H9>=参数!$D$2,参数!$E$2,IF(H9>=参数!$D$3,参数!$E$3,IF(H9>=参数!$D$4,参数!$E$4,IF(H9>=参数!$D$5,参数!$E$5,参数!$E$6))))) -> 0 | J9: =IF($A9="",0,C9*H9) -> 0 | K9: =IF($A9="",0,IF(J9>=参数!$G$2,参数!$H$2,IF(J9>=参数!$G$3,参数!$H$3,IF(J9>=参数!$G$4,参数!$H$4,IF(J9>=参数!$G$5,参数!$H$5,参数!$H$6))))) -> 0 | L9: =IF($A9="",0,I9*0.6+K9*0.4) -> 0 | P9: =IF($A9="",0,IF(M9>=参数!$J$2,参数!$K$2,IF(M9>=参数!$J$3,参数!$K$3,IF(M9>=参数!$J$4,参数!$K$4,IF(M9>=参数!$J$5,参数!$K$5,参数!$K$6))))) -> 0 | Q9: =IF($A9="",0,IF(M9=0,0,N9/M9)) -> 0 | R9: =IF($A9="",0,IF(Q9<参数!$M$2,参数!$N$2,IF(Q9<参数!$M$3,参数!$N$3,IF(Q9<参数!$M$4,参数!$N$4,IF(Q9<参数!$M$5,参数!$N$5,2))))) -> 0 | S9: =IF($A9="",0,IF(O9="上升",10,IF(O9="平稳",6,IF(O9="下降",2,6)))) -> 0 | T9: =IF($A9="",0,P9*0.4+R9*0.4+S9*0.2) -> 0 | W9: =IF($A9="",0,(L9*参数!$B$2+T9*参数!$B$3+U9*参数!$B$4+V9*参数!$B$5)*10) -> 0 | X9: =IF($A9="","",IF(B9="是",0,IF(OR(L9<参数!$B$8,T9<参数!$B$9),MIN(W9,参数!$B$10),W9))) | Y9: =IF($A9="","",IF(X9>=80,"主推",IF(X9>=65,"测款",IF(X9>=50,"观察","放弃"))))
H10: =IF($A10="",0,IF(C10=0,0,(C10-D10-C10*E10-F10-G10)/C10)) -> 0 | I10: =IF($A10="",0,IF(H10>=参数!$D$2,参数!$E$2,IF(H10>=参数!$D$3,参数!$E$3,IF(H10>=参数!$D$4,参数!$E$4,IF(H10>=参数!$D$5,参数!$E$5,参数!$E$6))))) -> 0 | J10: =IF($A10="",0,C10*H10) -> 0 | K10: =IF($A10="",0,IF(J10>=参数!$G$2,参数!$H$2,IF(J10>=参数!$G$3,参数!$H$3,IF(J10>=参数!$G$4,参数!$H$4,IF(J10>=参数!$G$5,参数!$H$5,参数!$H$6))))) -> 0 | L10: =IF($A10="",0,I10*0.6+K10*0.4) -> 0 | P10: =IF($A10="",0,IF(M10>=参数!$J$2,参数!$K$2,IF(M10>=参数!$J$3,参数!$K$3,IF(M10>=参数!$J$4,参数!$K$4,IF(M10>=参数!$J$5,参数!$K$5,参数!$K$6))))) -> 0 | Q10: =IF($A10="",0,IF(M10=0,0,N10/M10)) -> 0 | R10: =IF($A10="",0,IF(Q10<参数!$M$2,参数!$N$2,IF(Q10<参数!$M$3,参数!$N$3,IF(Q10<参数!$M$4,参数!$N$4,IF(Q10<参数!$M$5,参数!$N$5,2))))) -> 0 | S10: =IF($A10="",0,IF(O10="上升",10,IF(O10="平稳",6,IF(O10="下降",2,6)))) -> 0 | T10: =IF($A10="",0,P10*0.4+R10*0.4+S10*0.2) -> 0 | W10: =IF($A10="",0,(L10*参数!$B$2+T10*参数!$B$3+U10*参数!$B$4+V10*参数!$B$5)*10) -> 0 | X10: =IF($A10="","",IF(B10="是",0,IF(OR(L10<参数!$B$8,T10<参数!$B$9),MIN(W10,参数!$B$10),W10))) | Y10: =IF($A10="","",IF(X10>=80,"主推",IF(X10>=65,"测款",IF(X10>=50,"观察","放弃"))))
H11: =IF($A11="",0,IF(C11=0,0,(C11-D11-C11*E11-F11-G11)/C11)) -> 0 | I11: =IF($A11="",0,IF(H11>=参数!$D$2,参数!$E$2,IF(H11>=参数!$D$3,参数!$E$3,IF(H11>=参数!$D$4,参数!$E$4,IF(H11>=参数!$D$5,参数!$E$5,参数!$E$6))))) -> 0 | J11: =IF($A11="",0,C11*H11) -> 0 | K11: =IF($A11="",0,IF(J11>=参数!$G$2,参数!$H$2,IF(J11>=参数!$G$3,参数!$H$3,IF(J11>=参数!$G$4,参数!$H$4,IF(J11>=参数!$G$5,参数!$H$5,参数!$H$6))))) -> 0 | L11: =IF($A11="",0,I11*0.6+K11*0.4) -> 0 | P11: =IF($A11="",0,IF(M11>=参数!$J$2,参数!$K$2,IF(M11>=参数!$J$3,参数!$K$3,IF(M11>=参数!$J$4,参数!$K$4,IF(M11>=参数!$J$5,参数!$K$5,参数!$K$6))))) -> 0 | Q11: =IF($A11="",0,IF(M11=0,0,N11/M11)) -> 0 | R11: =IF($A11="",0,IF(Q11<参数!$M$2,参数!$N$2,IF(Q11<参数!$M$3,参数!$N$3,IF(Q11<参数!$M$4,参数!$N$4,IF(Q11<参数!$M$5,参数!$N$5,2))))) -> 0 | S11: =IF($A11="",0,IF(O11="上升",10,IF(O11="平稳",6,IF(O11="下降",2,6)))) -> 0 | T11: =IF($A11="",0,P11*0.4+R11*0.4+S11*0.2) -> 0 | W11: =IF($A11="",0,(L11*参数!$B$2+T11*参数!$B$3+U11*参数!$B$4+V11*参数!$B$5)*10) -> 0 | X11: =IF($A11="","",IF(B11="是",0,IF(OR(L11<参数!$B$8,T11<参数!$B$9),MIN(W11,参数!$B$10),W11))) | Y11: =IF($A11="","",IF(X11>=80,"主推",IF(X11>=65,"测款",IF(X11>=50,"观察","放弃"))))
H12: =IF($A12="",0,IF(C12=0,0,(C12-D12-C12*E12-F12-G12)/C12)) -> 0 | I12: =IF($A12="",0,IF(H12>=参数!$D$2,参数!$E$2,IF(H12>=参数!$D$3,参数!$E$3,IF(H12>=参数!$D$4,参数!$E$4,IF(H12>=参数!$D$5,参数!$E$5,参数!$E$6))))) -> 0 | J12: =IF($A12="",0,C12*H12) -> 0 | K12: =IF($A12="",0,IF(J12>=参数!$G$2,参数!$H$2,IF(J12>=参数!$G$3,参数!$H$3,IF(J12>=参数!$G$4,参数!$H$4,IF(J12>=参数!$G$5,参数!$H$5,参数!$H$6))))) -> 0 | L12: =IF($A12="",0,I12*0.6+K12*0.4) -> 0 | P12: =IF($A12="",0,IF(M12>=参数!$J$2,参数!$K$2,IF(M12>=参数!$J$3,参数!$K$3,IF(M12>=参数!$J$4,参数!$K$4,IF(M12>=参数!$J$5,参数!$K$5,参数!$K$6))))) -> 0 | Q12: =IF($A12="",0,IF(M12=0,0,N12/M12)) -> 0 | R12: =IF($A12="",0,IF(Q12<参数!$M$2,参数!$N$2,IF(Q12<参数!$M$3,参数!$N$3,IF(Q12<参数!$M$4,参数!$N$4,IF(Q12<参数!$M$5,参数!$N$5,2))))) -> 0 | S12: =IF($A12="",0,IF(O12="上升",10,IF(O12="平稳",6,IF(O12="下降",2,6)))) -> 0 | T12: =IF($A12="",0,P12*0.4+R12*0.4+S12*0.2) -> 0 | W12: =IF($A12="",0,(L12*参数!$B$2+T12*参数!$B$3+U12*参数!$B$4+V12*参数!$B$5)*10) -> 0 | X12: =IF($A12="","",IF(B12="是",0,IF(OR(L12<参数!$B$8,T12<参数!$B$9),MIN(W12,参数!$B$10),W12))) | Y12: =IF($A12="","",IF(X12>=80,"主推",IF(X12>=65,"测款",IF(X12>=50,"观察","放弃"))))
H13: =IF($A13="",0,IF(C13=0,0,(C13-D13-C13*E13-F13-G13)/C13)) -> 0 | I13: =IF($A13="",0,IF(H13>=参数!$D$2,参数!$E$2,IF(H13>=参数!$D$3,参数!$E$3,IF(H13>=参数!$D$4,参数!$E$4,IF(H13>=参数!$D$5,参数!$E$5,参数!$E$6))))) -> 0 | J13: =IF($A13="",0,C13*H13) -> 0 | K13: =IF($A13="",0,IF(J13>=参数!$G$2,参数!$H$2,IF(J13>=参数!$G$3,参数!$H$3,IF(J13>=参数!$G$4,参数!$H$4,IF(J13>=参数!$G$5,参数!$H$5,参数!$H$6))))) -> 0 | L13: =IF($A13="",0,I13*0.6+K13*0.4) -> 0 | P13: =IF($A13="",0,IF(M13>=参数!$J$2,参数!$K$2,IF(M13>=参数!$J$3,参数!$K$3,IF(M13>=参数!$J$4,参数!$K$4,IF(M13>=参数!$J$5,参数!$K$5,参数!$K$6))))) -> 0 | Q13: =IF($A13="",0,IF(M13=0,0,N13/M13)) -> 0 | R13: =IF($A13="",0,IF(Q13<参数!$M$2,参数!$N$2,IF(Q13<参数!$M$3,参数!$N$3,IF(Q13<参数!$M$4,参数!$N$4,IF(Q13<参数!$M$5,参数!$N$5,2))))) -> 0 | S13: =IF($A13="",0,IF(O13="上升",10,IF(O13="平稳",6,IF(O13="下降",2,6)))) -> 0 | T13: =IF($A13="",0,P13*0.4+R13*0.4+S13*0.2) -> 0 | W13: =IF($A13="",0,(L13*参数!$B$2+T13*参数!$B$3+U13*参数!$B$4+V13*参数!$B$5)*10) -> 0 | X13: =IF($A13="","",IF(B13="是",0,IF(OR(L13<参数!$B$8,T13<参数!$B$9),MIN(W13,参数!$B$10),W13))) | Y13: =IF($A13="","",IF(X13>=80,"主推",IF(X13>=65,"测款",IF(X13>=50,"观察","放弃"))))
H14: =IF($A14="",0,IF(C14=0,0,(C14-D14-C14*E14-F14-G14)/C14)) -> 0 | I14: =IF($A14="",0,IF(H14>=参数!$D$2,参数!$E$2,IF(H14>=参数!$D$3,参数!$E$3,IF(H14>=参数!$D$4,参数!$E$4,IF(H14>=参数!$D$5,参数!$E$5,参数!$E$6))))) -> 0 | J14: =IF($A14="",0,C14*H14) -> 0 | K14: =IF($A14="",0,IF(J14>=参数!$G$2,参数!$H$2,IF(J14>=参数!$G$3,参数!$H$3,IF(J14>=参数!$G$4,参数!$H$4,IF(J14>=参数!$G$5,参数!$H$5,参数!$H$6))))) -> 0 | L14: =IF($A14="",0,I14*0.6+K14*0.4) -> 0 | P14: =IF($A14="",0,IF(M14>=参数!$J$2,参数!$K$2,IF(M14>=参数!$J$3,参数!$K$3,IF(M14>=参数!$J$4,参数!$K$4,IF(M14>=参数!$J$5,参数!$K$5,参数!$K$6))))) -> 0 | Q14: =IF($A14="",0,IF(M14=0,0,N14/M14)) -> 0 | R14: =IF($A14="",0,IF(Q14<参数!$M$2,参数!$N$2,IF(Q14<参数!$M$3,参数!$N$3,IF(Q14<参数!$M$4,参数!$N$4,IF(Q14<参数!$M$5,参数!$N$5,2))))) -> 0 | S14: =IF($A14="",0,IF(O14="上升",10,IF(O14="平稳",6,IF(O14="下降",2,6)))) -> 0 | T14: =IF($A14="",0,P14*0.4+R14*0.4+S14*0.2) -> 0 | W14: =IF($A14="",0,(L14*参数!$B$2+T14*参数!$B$3+U14*参数!$B$4+V14*参数!$B$5)*10) -> 0 | X14: =IF($A14="","",IF(B14="是",0,IF(OR(L14<参数!$B$8,T14<参数!$B$9),MIN(W14,参数!$B$10),W14))) | Y14: =IF($A14="","",IF(X14>=80,"主推",IF(X14>=65,"测款",IF(X14>=50,"观察","放弃"))))
H15: =IF($A15="",0,IF(C15=0,0,(C15-D15-C15*E15-F15-G15)/C15)) -> 0 | I15: =IF($A15="",0,IF(H15>=参数!$D$2,参数!$E$2,IF(H15>=参数!$D$3,参数!$E$3,IF(H15>=参数!$D$4,参数!$E$4,IF(H15>=参数!$D$5,参数!$E$5,参数!$E$6))))) -> 0 | J15: =IF($A15="",0,C15*H15) -> 0 | K15: =IF($A15="",0,IF(J15>=参数!$G$2,参数!$H$2,IF(J15>=参数!$G$3,参数!$H$3,IF(J15>=参数!$G$4,参数!$H$4,IF(J15>=参数!$G$5,参数!$H$5,参数!$H$6))))) -> 0 | L15: =IF($A15="",0,I15*0.6+K15*0.4) -> 0 | P15: =IF($A15="",0,IF(M15>=参数!$J$2,参数!$K$2,IF(M15>=参数!$J$3,参数!$K$3,IF(M15>=参数!$J$4,参数!$K$4,IF(M15>=参数!$J$5,参数!$K$5,参数!$K$6))))) -> 0 | Q15: =IF($A15="",0,IF(M15=0,0,N15/M15)) -> 0 | R15: =IF($A15="",0,IF(Q15<参数!$M$2,参数!$N$2,IF(Q15<参数!$M$3,参数!$N$3,IF(Q15<参数!$M$4,参数!$N$4,IF(Q15<参数!$M$5,参数!$N$5,2))))) -> 0 | S15: =IF($A15="",0,IF(O15="上升",10,IF(O15="平稳",6,IF(O15="下降",2,6)))) -> 0 | T15: =IF($A15="",0,P15*0.4+R15*0.4+S15*0.2) -> 0 | W15: =IF($A15="",0,(L15*参数!$B$2+T15*参数!$B$3+U15*参数!$B$4+V15*参数!$B$5)*10) -> 0 | X15: =IF($A15="","",IF(B15="是",0,IF(OR(L15<参数!$B$8,T15<参数!$B$9),MIN(W15,参数!$B$10),W15))) | Y15: =IF($A15="","",IF(X15>=80,"主推",IF(X15>=65,"测款",IF(X15>=50,"观察","放弃"))))
H16: =IF($A16="",0,IF(C16=0,0,(C16-D16-C16*E16-F16-G16)/C16)) -> 0 | I16: =IF($A16="",0,IF(H16>=参数!$D$2,参数!$E$2,IF(H16>=参数!$D$3,参数!$E$3,IF(H16>=参数!$D$4,参数!$E$4,IF(H16>=参数!$D$5,参数!$E$5,参数!$E$6))))) -> 0 | J16: =IF($A16="",0,C16*H16) -> 0 | K16: =IF($A16="",0,IF(J16>=参数!$G$2,参数!$H$2,IF(J16>=参数!$G$3,参数!$H$3,IF(J16>=参数!$G$4,参数!$H$4,IF(J16>=参数!$G$5,参数!$H$5,参数!$H$6))))) -> 0 | L16: =IF($A16="",0,I16*0.6+K16*0.4) -> 0 | P16: =IF($A16="",0,IF(M16>=参数!$J$2,参数!$K$2,IF(M16>=参数!$J$3,参数!$K$3,IF(M16>=参数!$J$4,参数!$K$4,IF(M16>=参数!$J$5,参数!$K$5,参数!$K$6))))) -> 0 | Q16: =IF($A16="",0,IF(M16=0,0,N16/M16)) -> 0 | R16: =IF($A16="",0,IF(Q16<参数!$M$2,参数!$N$2,IF(Q16<参数!$M$3,参数!$N$3,IF(Q16<参数!$M$4,参数!$N$4,IF(Q16<参数!$M$5,参数!$N$5,2))))) -> 0 | S16: =IF($A16="",0,IF(O16="上升",10,IF(O16="平稳",6,IF(O16="下降",2,6)))) -> 0 | T16: =IF($A16="",0,P16*0.4+R16*0.4+S16*0.2) -> 0 | W16: =IF($A16="",0,(L16*参数!$B$2+T16*参数!$B$3+U16*参数!$B$4+V16*参数!$B$5)*10) -> 0 | X16: =IF($A16="","",IF(B16="是",0,IF(OR(L16<参数!$B$8,T16<参数!$B$9),MIN(W16,参数!$B$10),W16))) | Y16: =IF($A16="","",IF(X16>=80,"主推",IF(X16>=65,"测款",IF(X16>=50,"观察","放弃"))))
H17: =IF($A17="",0,IF(C17=0,0,(C17-D17-C17*E17-F17-G17)/C17)) -> 0 | I17: =IF($A17="",0,IF(H17>=参数!$D$2,参数!$E$2,IF(H17>=参数!$D$3,参数!$E$3,IF(H17>=参数!$D$4,参数!$E$4,IF(H17>=参数!$D$5,参数!$E$5,参数!$E$6))))) -> 0 | J17: =IF($A17="",0,C17*H17) -> 0 | K17: =IF($A17="",0,IF(J17>=参数!$G$2,参数!$H$2,IF(J17>=参数!$G$3,参数!$H$3,IF(J17>=参数!$G$4,参数!$H$4,IF(J17>=参数!$G$5,参数!$H$5,参数!$H$6))))) -> 0 | L17: =IF($A17="",0,I17*0.6+K17*0.4) -> 0 | P17: =IF($A17="",0,IF(M17>=参数!$J$2,参数!$K$2,IF(M17>=参数!$J$3,参数!$K$3,IF(M17>=参数!$J$4,参数!$K$4,IF(M17>=参数!$J$5,参数!$K$5,参数!$K$6))))) -> 0 | Q17: =IF($A17="",0,IF(M17=0,0,N17/M17)) -> 0 | R17: =IF($A17="",0,IF(Q17<参数!$M$2,参数!$N$2,IF(Q17<参数!$M$3,参数!$N$3,IF(Q17<参数!$M$4,参数!$N$4,IF(Q17<参数!$M$5,参数!$N$5,2))))) -> 0 | S17: =IF($A17="",0,IF(O17="上升",10,IF(O17="平稳",6,IF(O17="下降",2,6)))) -> 0 | T17: =IF($A17="",0,P17*0.4+R17*0.4+S17*0.2) -> 0 | W17: =IF($A17="",0,(L17*参数!$B$2+T17*参数!$B$3+U17*参数!$B$4+V17*参数!$B$5)*10) -> 0 | X17: =IF($A17="","",IF(B17="是",0,IF(OR(L17<参数!$B$8,T17<参数!$B$9),MIN(W17,参数!$B$10),W17))) | Y17: =IF($A17="","",IF(X17>=80,"主推",IF(X17>=65,"测款",IF(X17>=50,"观察","放弃"))))
H18: =IF($A18="",0,IF(C18=0,0,(C18-D18-C18*E18-F18-G18)/C18)) -> 0 | I18: =IF($A18="",0,IF(H18>=参数!$D$2,参数!$E$2,IF(H18>=参数!$D$3,参数!$E$3,IF(H18>=参数!$D$4,参数!$E$4,IF(H18>=参数!$D$5,参数!$E$5,参数!$E$6))))) -> 0 | J18: =IF($A18="",0,C18*H18) -> 0 | K18: =IF($A18="",0,IF(J18>=参数!$G$2,参数!$H$2,IF(J18>=参数!$G$3,参数!$H$3,IF(J18>=参数!$G$4,参数!$H$4,IF(J18>=参数!$G$5,参数!$H$5,参数!$H$6))))) -> 0 | L18: =IF($A18="",0,I18*0.6+K18*0.4) -> 0 | P18: =IF($A18="",0,IF(M18>=参数!$J$2,参数!$K$2,IF(M18>=参数!$J$3,参数!$K$3,IF(M18>=参数!$J$4,参数!$K$4,IF(M18>=参数!$J$5,参数!$K$5,参数!$K$6))))) -> 0 | Q18: =IF($A18="",0,IF(M18=0,0,N18/M18)) -> 0 | R18: =IF($A18="",0,IF(Q18<参数!$M$2,参数!$N$2,IF(Q18<参数!$M$3,参数!$N$3,IF(Q18<参数!$M$4,参数!$N$4,IF(Q18<参数!$M$5,参数!$N$5,2))))) -> 0 | S18: =IF($A18="",0,IF(O18="上升",10,IF(O18="平稳",6,IF(O18="下降",2,6)))) -> 0 | T18: =IF($A18="",0,P18*0.4+R18*0.4+S18*0.2) -> 0 | W18: =IF($A18="",0,(L18*参数!$B$2+T18*参数!$B$3+U18*参数!$B$4+V18*参数!$B$5)*10) -> 0 | X18: =IF($A18="","",IF(B18="是",0,IF(OR(L18<参数!$B$8,T18<参数!$B$9),MIN(W18,参数!$B$10),W18))) | Y18: =IF($A18="","",IF(X18>=80,"主推",IF(X18>=65,"测款",IF(X18>=50,"观察","放弃"))))
H19: =IF($A19="",0,IF(C19=0,0,(C19-D19-C19*E19-F19-G19)/C19)) -> 0 | I19: =IF($A19="",0,IF(H19>=参数!$D$2,参数!$E$2,IF(H19>=参数!$D$3,参数!$E$3,IF(H19>=参数!$D$4,参数!$E$4,IF(H19>=参数!$D$5,参数!$E$5,参数!$E$6))))) -> 0 | J19: =IF($A19="",0,C19*H19) -> 0 | K19: =IF($A19="",0,IF(J19>=参数!$G$2,参数!$H$2,IF(J19>=参数!$G$3,参数!$H$3,IF(J19>=参数!$G$4,参数!$H$4,IF(J19>=参数!$G$5,参数!$H$5,参数!$H$6))))) -> 0 | L19: =IF($A19="",0,I19*0.6+K19*0.4) -> 0 | P19: =IF($A19="",0,IF(M19>=参数!$J$2,参数!$K$2,IF(M19>=参数!$J$3,参数!$K$3,IF(M19>=参数!$J$4,参数!$K$4,IF(M19>=参数!$J$5,参数!$K$5,参数!$K$6))))) -> 0 | Q19: =IF($A19="",0,IF(M19=0,0,N19/M19)) -> 0 | R19: =IF($A19="",0,IF(Q19<参数!$M$2,参数!$N$2,IF(Q19<参数!$M$3,参数!$N$3,IF(Q19<参数!$M$4,参数!$N$4,IF(Q19<参数!$M$5,参数!$N$5,2))))) -> 0 | S19: =IF($A19="",0,IF(O19="上升",10,IF(O19="平稳",6,IF(O19="下降",2,6)))) -> 0 | T19: =IF($A19="",0,P19*0.4+R19*0.4+S19*0.2) -> 0 | W19: =IF($A19="",0,(L19*参数!$B$2+T19*参数!$B$3+U19*参数!$B$4+V19*参数!$B$5)*10) -> 0 | X19: =IF($A19="","",IF(B19="是",0,IF(OR(L19<参数!$B$8,T19<参数!$B$9),MIN(W19,参数!$B$10),W19))) | Y19: =IF($A19="","",IF(X19>=80,"主推",IF(X19>=65,"测款",IF(X19>=50,"观察","放弃"))))
... H23: =IF($A23="",0,IF(C23=0,0,(C23-D23-C23*E23-F23-G23)/C23)) -> 0 | I23: =IF($A23="",0,IF(H23>=参数!$D$2,参数!$E$2,IF(H23>=参数!$D$3,参数!$E$3,IF(H23>=参数!$D$4,参数!$E$4,IF(H23>=参数!$D$5,参数!$E$5,参数!$E$6))))) -> 0 | J23: =IF($A23="",0,C23*H23) -> 0 | K23: =IF($A23="",0,IF(J23>=参数!$G$2,参数!$H$2,IF(J23>=参数!$G$3,参数!$H$3,IF(J23>=参数!$G$4,参数!$H$4,IF(J23>=参数!$G$5,参数!$H$5,参数!$H$6))))) -> 0 | L23: =IF($A23="",0,I23*0.6+K23*0.4) -> 0 | P23: =IF($A23="",0,IF(M23>=参数!$J$2,参数!$K$2,IF(M23>=参数!$J$3,参数!$K$3,IF(M23>=参数!$J$4,参数!$K$4,IF(M23>=参数!$J$5,参数!$K$5,参数!$K$6))))) -> 0 | Q23: =IF($A23="",0,IF(M23=0,0,N23/M23)) -> 0 | R23: =IF($A23="",0,IF(Q23<参数!$M$2,参数!$N$2,IF(Q23<参数!$M$3,参数!$N$3,IF(Q23<参数!$M$4,参数!$N$4,IF(Q23<参数!$M$5,参数!$N$5,2))))) -> 0 | S23: =IF($A23="",0,IF(O23="上升",10,IF(O23="平稳",6,IF(O23="下降",2,6)))) -> 0 | T23: =IF($A23="",0,P23*0.4+R23*0.4+S23*0.2) -> 0 | W23: =IF($A23="",0,(L23*参数!$B$2+T23*参数!$B$3+U23*参数!$B$4+V23*参数!$B$5)*10) -> 0 | X23: =IF($A23="","",IF(B23="是",0,IF(OR(L23<参数!$B$8,T23<参数!$B$9),MIN(W23,参数!$B$10),W23))) | Y23: =IF($A23="","",IF(X23>=80,"主推",IF(X23>=65,"测款",IF(X23>=50,"观察","放弃"))))

Sheet 参数
A1: 权重（按店铺阶段可调） | D1: 毛利率阈值 | E1: 得分 | G1: 绝对利润额阈值 | H1: 得分 | J1: 搜索人气阈值 | K1: 得分 | M1: 竞争度阈值(<) | N1: 得分
A2: 利润 | B2: 0.3 | D2: 0.6 | E2: 10 | G2: 50 | H2: 10 | J2: 10000 | K2: 10 | M2: 1 | N2: 10
A3: 蓝海度 | B3: 0.3 | D3: 0.5 | E3: 8 | G3: 30 | H3: 8 | J3: 5000 | K3: 8 | M3: 3 | N3: 8
A4: 复购 | B4: 0.25 | D4: 0.4 | E4: 6 | G4: 20 | H4: 6 | J4: 2000 | K4: 6 | M4: 6 | N4: 6
A5: 合规难度 | B5: 0.15 | D5: 0.3 | E5: 4 | G5: 10 | H5: 4 | J5: 500 | K5: 4 | M5: 10 | N5: 4
D6: 0 | E6: 2 | G6: 0 | H6: 2 | J6: 0 | K6: 2
A7: 底线/封顶
A8: 利润底线 | B8: 4
A9: 蓝海度底线 | B9: 3
A10: 封顶分 | B10: 50
